{
  "Name": "19 - Mensaje de pepe a maria con pdf adjunto",
  "CreationDate": "2022-4-15",
  "Commands": [
    {
      "Command": "open",
      "Target": "http://localhost/Taller2/index.php",
      "Value": "",
      "Description": ""
    },
    {
      "Command": "type",
      "Target": "id=txtUsuario",
      "Value": "pepe",
      "Targets": [
        "id=txtUsuario",
        "name=txtUsuario",
        "xpath=//*[@id=\"txtUsuario\"]",
        "xpath=//input[@id='txtUsuario']",
        "xpath=//p[2]/input",
        "css=#txtUsuario"
      ],
      "Description": ""
    },
    {
      "Command": "type",
      "Target": "id=txtClave",
      "Value": "*Abc123+",
      "Targets": [
        "id=txtClave",
        "name=txtClave",
        "xpath=//*[@id=\"txtClave\"]",
        "xpath=//input[@id='txtClave']",
        "xpath=//p[3]/input",
        "css=#txtClave"
      ],
      "Description": ""
    },
    {
      "Command": "clickAndWait",
      "Target": "name=btnIngresar",
      "Value": "",
      "Targets": [
        "name=btnIngresar",
        "xpath=/html/body/div[3]/form/p[4]/input",
        "xpath=//input[@name='btnIngresar']",
        "xpath=//p[4]/input",
        "css=body > div.login > form:nth-child(3) > p:nth-child(4) > input"
      ],
      "Description": ""
    },
    {
      "Command": "clickAndWait",
      "Target": "name=lnkMensajes",
      "Value": "",
      "Targets": [
        "name=lnkMensajes",
        "xpath=/html/body/div[2]/div/form/input[2]",
        "xpath=//input[@name='lnkMensajes']",
        "xpath=//div[2]/div/form/input[2]",
        "css=body > div:nth-child(6) > div > form > input:nth-child(4)"
      ],
      "Description": ""
    },
    {
      "Command": "clickAndWait",
      "Target": "name=lnkRecibidos",
      "Value": "",
      "Targets": [
        "name=lnkRecibidos",
        "xpath=/html/body/div[2]/div/form/input[3]",
        "xpath=//input[@name='lnkRecibidos']",
        "xpath=//input[3]",
        "css=body > div:nth-child(9) > div > form > input:nth-child(4)"
      ],
      "Description": ""
    },
    {
      "Command": "click",
      "Target": "name=cmbDestino",
      "Value": "",
      "Targets": [
        "name=cmbDestino",
        "xpath=/html/body/div[3]/form/p[2]/select",
        "xpath=//select[@name='cmbDestino']",
        "xpath=//select",
        "css=body > div.login > form > p:nth-child(2) > select"
      ],
      "Description": ""
    },
    {
      "Command": "select",
      "Target": "name=cmbDestino",
      "Value": "label=maria",
      "Targets": [
        "name=cmbDestino",
        "xpath=/html/body/div[3]/form/p[2]/select",
        "xpath=//select[@name='cmbDestino']",
        "xpath=//select",
        "css=body > div.login > form > p:nth-child(2) > select"
      ],
      "Description": ""
    },
    {
      "Command": "click",
      "Target": "name=cmbDestino",
      "Value": "",
      "Targets": [
        "name=cmbDestino",
        "xpath=/html/body/div[3]/form/p[2]/select",
        "xpath=//select[@name='cmbDestino']",
        "xpath=//select",
        "css=body > div.login > form > p:nth-child(2) > select"
      ],
      "Description": ""
    },
    {
      "Command": "click",
      "Target": "id=txtMensaje",
      "Value": "",
      "Targets": [
        "id=txtMensaje",
        "name=txtMensaje",
        "xpath=//*[@id=\"txtMensaje\"]",
        "xpath=//textarea[@id='txtMensaje']",
        "xpath=//textarea",
        "css=#txtMensaje"
      ],
      "Description": ""
    },
    {
      "Command": "type",
      "Target": "id=txtMensaje",
      "Value": "hola maría.",
      "Targets": [
        "id=txtMensaje",
        "name=txtMensaje",
        "xpath=//*[@id=\"txtMensaje\"]",
        "xpath=//textarea[@id='txtMensaje']",
        "xpath=//textarea",
        "css=#txtMensaje"
      ],
      "Description": ""
    },
    {
      "Command": "XClick",
      "Target": "name=fulAdjunto",
      "Value": "",
      "Targets": [
        "name=fulAdjunto",
        "xpath=/html/body/div[3]/form/p[4]/input",
        "xpath=//input[@name='fulAdjunto']",
        "xpath=//p[4]/input",
        "css=body > div.login > form > p:nth-child(4) > input"
      ],
      "Description": ""
    },
    {
      "Command": "XType",
      "Target": "C:\\tmp\\tmp.jpg",
      "Value": "",
      "Description": ""
    },
    {
      "Command": "XType",
      "Target": "${KEY_ENTER}",
      "Value": "",
      "Description": ""
    },
    {
      "Command": "click",
      "Target": "name=btnEnviar",
      "Value": "",
      "Targets": [
        "name=btnEnviar",
        "xpath=/html/body/div[3]/form/p[5]/input",
        "xpath=//input[@name='btnEnviar']",
        "xpath=//p[5]/input",
        "css=body > div.login > form > p:nth-child(5) > input"
      ],
      "Description": ""
    },
    {
      "Command": "verifyText",
      "Target": "name=notificacion",
      "Value": "Mensaje enviado",
      "Description": ""
    }
  ]
}